{
  "project_info": {
    "project_number": "174410583131",
    "firebase_url": "https://keptureone-2563f.firebaseio.com",
    "project_id": "keptureone-2563f",
    "storage_bucket": "keptureone-2563f.appspot.com"
  },
  "client": [
    {
      "client_info": {
        "mobilesdk_app_id": "1:174410583131:android:2b6a2c700ca3dd34",
        "android_client_info": {
          "package_name": "com.ko.kaptureone"
        }
      },
      "oauth_client": [
        {
          "client_id": "174410583131-ij60fno67abo1l41pkoi4m2u19ctsggi.apps.googleusercontent.com",
          "client_type": 1,
          "android_info": {
            "package_name": "com.ko.kaptureone",
            "certificate_hash": "52b38d9e3e443880a6f1bca810b445fcefc63fef"
          }
        },
        {
          "client_id": "174410583131-qg1tlmmamhd7r6gq3690vt1fok7q8blj.apps.googleusercontent.com",
          "client_type": 3
        }
      ],
      "api_key": [
        {
          "current_key": "AIzaSyDg6zO6LdRjX-SfgVKbfQpAlRUb8IgJ_q4"
        }
      ],
      "services": {
        "appinvite_service": {
          "other_platform_oauth_client": [
            {
              "client_id": "174410583131-qg1tlmmamhd7r6gq3690vt1fok7q8blj.apps.googleusercontent.com",
              "client_type": 3
            },
            {
              "client_id": "174410583131-eu5cfi0o0vp4vgtglreo2qm7ser2hf7g.apps.googleusercontent.com",
              "client_type": 2,
              "ios_info": {
                "bundle_id": "com.ko.kaptureone"
              }
            }
          ]
        }
      }
    }
  ],
  "configuration_version": "1"
}